{"type":"FeatureCollection","crs":{"type":"name","properties":{"name":"EPSG:4326"}},"features":[{"type":"Feature","id":1,"geometry":{"type":"Point","coordinates":[120.33669731900011,31.946819704000063]},"properties":{"OBJECTID":1,"ID":1,"X":531769.16235500004,"Y":3536044.0963889998,"Z":0,"地名":"大河港"}},{"type":"Feature","id":2,"geometry":{"type":"Point","coordinates":[120.38313145400002,31.971079972000041]},"properties":{"OBJECTID":2,"ID":2,"X":536149.92029399995,"Y":3538748.831458,"Z":0,"地名":"福南水道"}},{"type":"Feature","id":3,"geometry":{"type":"Point","coordinates":[121.51070722400004,31.796812357000078]},"properties":{"OBJECTID":3,"ID":3,"X":643007.85582699999,"Y":3520354.865152,"Z":0,"地名":"三和港"}},{"type":"Feature","id":4,"geometry":{"type":"Point","coordinates":[120.70992977600008,31.990596778000054]},"properties":{"OBJECTID":4,"ID":4,"X":567026.23439999996,"Y":3541069.0117609999,"Z":0,"地名":"十三圩港"}},{"type":"Feature","id":5,"geometry":{"type":"Point","coordinates":[120.66692598400004,31.99035604900007]},"properties":{"OBJECTID":5,"ID":5,"X":562962.29331500002,"Y":3541016.4547100002,"Z":0,"地名":"十一圩港"}},{"type":"Feature","id":6,"geometry":{"type":"Point","coordinates":[120.44919750700001,31.971831597000062]},"properties":{"OBJECTID":6,"ID":6,"X":542394.39178299997,"Y":3538856.1817859998,"Z":0,"地名":"十字港"}},{"type":"Feature","id":7,"geometry":{"type":"Point","coordinates":[120.3857844690001,31.962837601000047]},"properties":{"OBJECTID":7,"ID":7,"X":536403.94924500003,"Y":3537835.7476940001,"Z":0,"地名":"巫山港"}},{"type":"Feature","id":8,"geometry":{"type":"Point","coordinates":[120.40745108500005,31.965685146000055]},"properties":{"OBJECTID":8,"ID":8,"X":538450.95374899998,"Y":3538159.0058249999,"Z":0,"地名":"张家港"}},{"type":"Feature","id":9,"geometry":{"type":"Point","coordinates":[120.37085515900003,32.043323675000067]},"properties":{"OBJECTID":9,"ID":9,"X":534962.05375099997,"Y":3546755.7436190001,"Z":0,"地名":"安宁港"}},{"type":"Feature","id":10,"geometry":{"type":"Point","coordinates":[120.4248893140001,31.964922803000036]},"properties":{"OBJECTID":10,"ID":10,"X":540099.71027599997,"Y":3538080.8069389998,"Z":0,"地名":"老套港"}},{"type":"Feature","id":11,"geometry":{"type":"Point","coordinates":[121.46455270200011,31.761858381000025]},"properties":{"OBJECTID":11,"ID":11,"X":638688.50783100002,"Y":3516418.6894589998,"Z":0,"地名":"沙"}},{"type":"Feature","id":12,"geometry":{"type":"Point","coordinates":[121.45338009400007,31.771782381000037]},"properties":{"OBJECTID":12,"ID":12,"X":637615.20178200002,"Y":3517505.0577540002,"Z":0,"地名":"隆"}},{"type":"Feature","id":13,"geometry":{"type":"Point","coordinates":[121.43924961100004,31.778312335000066]},"properties":{"OBJECTID":13,"ID":13,"X":636266.90122100001,"Y":3518211.4256589999,"Z":0,"地名":"永"}},{"type":"Feature","id":14,"geometry":{"type":"Point","coordinates":[121.58637460600005,31.713887613000054]},"properties":{"OBJECTID":14,"ID":14,"X":650308.81962299999,"Y":3511260.4532880001,"Z":0,"地名":"沙"}},{"type":"Feature","id":15,"geometry":{"type":"Point","coordinates":[121.55062788000009,31.731519817000049]},"properties":{"OBJECTID":15,"ID":15,"X":646892.15317900002,"Y":3513167.0954390001,"Z":0,"地名":"隆"}},{"type":"Feature","id":16,"geometry":{"type":"Point","coordinates":[121.51153747800004,31.751589683000077]},"properties":{"OBJECTID":16,"ID":16,"X":643156.16891699994,"Y":3515340.7580090002,"Z":0,"地名":"新"}},{"type":"Feature","id":17,"geometry":{"type":"Point","coordinates":[121.32953350800005,31.661515980000047]},"properties":{"OBJECTID":17,"ID":17,"X":626031.27992999996,"Y":3505126.9990320001,"Z":0,"地名":"鸽笼港"}},{"type":"Feature","id":18,"geometry":{"type":"Point","coordinates":[121.35215606700001,31.470861416000048]},"properties":{"OBJECTID":18,"ID":18,"X":628438.23226900003,"Y":3484011.054515,"Z":0,"地名":"石洞口电厂"}},{"type":"Feature","id":19,"geometry":{"type":"Point","coordinates":[121.59629081100002,31.531756588000064]},"properties":{"OBJECTID":19,"ID":19,"X":651543.98332200001,"Y":3491075.906585,"Z":0,"地名":"堡镇港"}},{"type":"Feature","id":20,"geometry":{"type":"Point","coordinates":[121.47690481200004,31.590101553000068]},"properties":{"OBJECTID":20,"ID":20,"X":640116.71594300005,"Y":3497387.060426,"Z":0,"地名":"东平河"}},{"type":"Feature","id":21,"geometry":{"type":"Point","coordinates":[121.51615045400001,31.570220347000031]},"properties":{"OBJECTID":21,"ID":21,"X":643872.694197,"Y":3495233.2687309999,"Z":0,"地名":"新河港"}},{"type":"Feature","id":22,"geometry":{"type":"Point","coordinates":[121.16750651300003,31.763591840000061]},"properties":{"OBJECTID":22,"ID":22,"X":610541.98000800004,"Y":3516270.6310709999,"Z":0,"地名":"白茆沙北水道"}},{"type":"Feature","id":23,"geometry":{"type":"Point","coordinates":[121.3541884440001,31.586469102000024]},"properties":{"OBJECTID":23,"ID":23,"X":628472.94731199997,"Y":3496833.4810879999,"Z":0,"地名":"下扁担沙"}},{"type":"Feature","id":24,"geometry":{"type":"Point","coordinates":[121.27407576200005,31.681999963000067]},"properties":{"OBJECTID":24,"ID":24,"X":620744.61116700002,"Y":3507335.8049789998,"Z":0,"地名":"上扁担沙"}},{"type":"Feature","id":25,"geometry":{"type":"Point","coordinates":[121.12559667200003,31.715085594000072]},"properties":{"OBJECTID":25,"ID":25,"X":606626.88986999996,"Y":3510849.8601779998,"Z":0,"地名":"茆沙南"}},{"type":"Feature","id":26,"geometry":{"type":"Point","coordinates":[121.28997682700003,31.702491694000059]},"properties":{"OBJECTID":26,"ID":26,"X":622225.60717900004,"Y":3509625.9360750001,"Z":0,"地名":"庙港新闸"}},{"type":"Feature","id":27,"geometry":{"type":"Point","coordinates":[121.2091722990001,31.744323386000076]},"properties":{"OBJECTID":27,"ID":27,"X":614513.28940999997,"Y":3514176.9816109999,"Z":0,"地名":"新建水闸"}},{"type":"Feature","id":28,"geometry":{"type":"Point","coordinates":[121.19588093900006,31.75986991700006]},"properties":{"OBJECTID":28,"ID":28,"X":613234.815069,"Y":3515887.079626,"Z":0,"地名":"崇西水闸"}},{"type":"Feature","id":29,"geometry":{"type":"Point","coordinates":[121.15970216100004,31.640622848000078]},"properties":{"OBJECTID":29,"ID":29,"X":609947.60117399995,"Y":3502626.4746599998,"Z":0,"地名":"浪港闸"}},{"type":"Feature","id":30,"geometry":{"type":"Point","coordinates":[121.20733954500008,31.604811109000025]},"properties":{"OBJECTID":30,"ID":30,"X":614510.78470399999,"Y":3498704.2323110001,"Z":0,"地名":"七浦闸"}},{"type":"Feature","id":31,"geometry":{"type":"Point","coordinates":[121.38733598700003,31.622611867000046]},"properties":{"OBJECTID":31,"ID":31,"X":631568.68651100004,"Y":3500880.9504900002,"Z":0,"地名":"南门港"}},{"type":"Feature","id":32,"geometry":{"type":"Point","coordinates":[121.08273572500002,31.69675692800007]},"properties":{"OBJECTID":32,"ID":32,"X":602584.19669500005,"Y":3508776.2275200002,"Z":0,"地名":"新泾河"}},{"type":"Feature","id":33,"geometry":{"type":"Point","coordinates":[121.23101188400005,31.580854481000074]},"properties":{"OBJECTID":33,"ID":33,"X":616787.329593,"Y":3496072.7030489999,"Z":0,"地名":"杨林"}},{"type":"Feature","id":34,"geometry":{"type":"Point","coordinates":[120.62255772600008,32.02233990600007]},"properties":{"OBJECTID":34,"ID":34,"X":558748.82491900004,"Y":3544538.147626,"Z":0,"地名":"泓北沙"}},{"type":"Feature","id":35,"geometry":{"type":"Point","coordinates":[120.7195602490001,32.022169208000037]},"properties":{"OBJECTID":35,"ID":35,"X":567913.073661,"Y":3544576.114635,"Z":0,"地名":"横港沙"}},{"type":"Feature","id":36,"geometry":{"type":"Point","coordinates":[120.53143844100009,32.037886082000057]},"properties":{"OBJECTID":36,"ID":36,"X":550132.10037500004,"Y":3546216.1031180001,"Z":0,"地名":"民主沙"}},{"type":"Feature","id":37,"geometry":{"type":"Point","coordinates":[120.35051604700004,32.027100874000041]},"properties":{"OBJECTID":37,"ID":37,"X":533046.86953999999,"Y":3544950.4130119998,"Z":0,"地名":"和尚港"}},{"type":"Feature","id":38,"geometry":{"type":"Point","coordinates":[120.41670050500011,32.069519356000058]},"properties":{"OBJECTID":38,"ID":38,"X":539280.92231699999,"Y":3549676.3375690002,"Z":0,"地名":"丹华港"}},{"type":"Feature","id":39,"geometry":{"type":"Point","coordinates":[120.46636340000009,32.085091520000049]},"properties":{"OBJECTID":39,"ID":39,"X":543962.77896400006,"Y":3551422.3075799998,"Z":0,"地名":"焦港"}},{"type":"Feature","id":40,"geometry":{"type":"Point","coordinates":[120.31550964700011,31.93813082500003]},"properties":{"OBJECTID":40,"ID":40,"X":529768.70965900004,"Y":3535074.5882390002,"Z":0,"地名":"白屈港"}},{"type":"Feature","id":41,"geometry":{"type":"Point","coordinates":[120.29543624100006,31.999302360000058]},"properties":{"OBJECTID":41,"ID":41,"X":527852.12276699999,"Y":3541852.3580700001,"Z":0,"地名":"蟛蜞港"}},{"type":"Feature","id":42,"geometry":{"type":"Point","coordinates":[120.82136902500008,32.008919245000072]},"properties":{"OBJECTID":42,"ID":42,"X":577542.53269499994,"Y":3543175.3642569999,"Z":7,"地名":"任港"}},{"type":"Feature","id":43,"geometry":{"type":"Point","coordinates":[120.52695346500002,32.002152559000024]},"properties":{"OBJECTID":43,"ID":43,"X":549727.78232200001,"Y":3542251.5675840001,"Z":0,"地名":"段山港"}},{"type":"Feature","id":44,"geometry":{"type":"Point","coordinates":[120.5031609880001,32.008741361000034]},"properties":{"OBJECTID":44,"ID":44,"X":547476.17083299998,"Y":3542971.4855999998,"Z":0,"地名":"太字港"}},{"type":"Feature","id":45,"geometry":{"type":"Point","coordinates":[120.71291905500004,32.067002737000053]},"properties":{"OBJECTID":45,"ID":45,"X":567252.84284499998,"Y":3549543.6057059998,"Z":0,"地名":"捕鱼港"}},{"type":"Feature","id":46,"geometry":{"type":"Point","coordinates":[120.74215398500007,32.049268331000064]},"properties":{"OBJECTID":46,"ID":46,"X":570026.94617200003,"Y":3547595.6099729999,"Z":7,"地名":"九圩港"}},{"type":"Feature","id":47,"geometry":{"type":"Point","coordinates":[120.67155483900001,32.063163379000059]},"properties":{"OBJECTID":47,"ID":47,"X":563349.57826600003,"Y":3549092.8077460001,"Z":7,"地名":"小李港"}},{"type":"Feature","id":48,"geometry":{"type":"Point","coordinates":[120.68760754800007,31.989691785000048]},"properties":{"OBJECTID":48,"ID":48,"X":564917.29129800003,"Y":3540955.0305929999,"Z":0,"地名":"十二圩港"}},{"type":"Feature","id":49,"geometry":{"type":"Point","coordinates":[120.60468756200009,31.985405213000035]},"properties":{"OBJECTID":49,"ID":49,"X":557083.48496999999,"Y":3540432.8923599999,"Z":0,"地名":"一干河"}},{"type":"Feature","id":50,"geometry":{"type":"Point","coordinates":[120.5618016200001,31.992094247000068]},"properties":{"OBJECTID":50,"ID":50,"X":553026.47369100002,"Y":3541152.7847000002,"Z":0,"地名":"渡泾港"}},{"type":"Feature","id":51,"geometry":{"type":"Point","coordinates":[120.54437245500003,31.99609956200004]},"properties":{"OBJECTID":51,"ID":51,"X":551377.12780699995,"Y":3541588.5089130001,"Z":0,"地名":"朝东圩港"}},{"type":"Feature","id":52,"geometry":{"type":"Point","coordinates":[120.78351818500005,31.861115197000061]},"properties":{"OBJECTID":52,"ID":52,"X":574084.61055800004,"Y":3526758.7978229998,"Z":0,"地名":"长沙河"}},{"type":"Feature","id":53,"geometry":{"type":"Point","coordinates":[120.75372318800009,31.890104288000032]},"properties":{"OBJECTID":53,"ID":53,"X":571242.51489999995,"Y":3529953.4020770001,"Z":0,"地名":"农场水闸"}},{"type":"Feature","id":54,"geometry":{"type":"Point","coordinates":[120.73724844900005,31.951259553000057]},"properties":{"OBJECTID":54,"ID":54,"X":569637.726823,"Y":3536724.1640650001,"Z":0,"地名":"五干河"}},{"type":"Feature","id":55,"geometry":{"type":"Point","coordinates":[120.75061615400011,31.910704266000039]},"properties":{"OBJECTID":55,"ID":55,"X":570932.75037300005,"Y":3532235.6797759999,"Z":0,"地名":"六干河"}},{"type":"Feature","id":56,"geometry":{"type":"Point","coordinates":[120.93927033600005,31.855861230000073]},"properties":{"OBJECTID":56,"ID":56,"X":588830.03966500005,"Y":3526293.1373379999,"Z":0,"地名":"南农闸"}},{"type":"Feature","id":57,"geometry":{"type":"Point","coordinates":[121.00665028500009,31.751646125000036]},"properties":{"OBJECTID":57,"ID":57,"X":595314.32113299996,"Y":3514793.7701619999,"Z":0,"地名":"金泾塘口"}},{"type":"Feature","id":58,"geometry":{"type":"Point","coordinates":[121.15578847500001,31.800556708000045]},"properties":{"OBJECTID":58,"ID":58,"X":609388.22344199999,"Y":3520357.9300919999,"Z":0,"地名":"长江北支"}},{"type":"Feature","id":59,"geometry":{"type":"Point","coordinates":[120.95196184300005,31.819982423000056]},"properties":{"OBJECTID":59,"ID":59,"X":590066.11070199998,"Y":3522324.9710530001,"Z":0,"地名":"港德码头"}},{"type":"Feature","id":60,"geometry":{"type":"Point","coordinates":[121.10090204300002,31.820051180000064]},"properties":{"OBJECTID":60,"ID":60,"X":604168.29526200006,"Y":3522465.7832570001,"Z":0,"地名":"海太汽渡"}},{"type":"Feature","id":61,"geometry":{"type":"Point","coordinates":[121.02107561600008,31.716409562000024]},"properties":{"OBJECTID":61,"ID":61,"X":596717.79423799994,"Y":3510899.1130289999,"Z":0,"地名":"白茆河"}},{"type":"Feature","id":62,"geometry":{"type":"Point","coordinates":[121.06333198300001,31.836913835000075]},"properties":{"OBJECTID":62,"ID":62,"X":600592.68433700001,"Y":3524300.3014469999,"Z":0,"地名":"新江海河"}},{"type":"Feature","id":63,"geometry":{"type":"Point","coordinates":[121.02028863600003,31.841039652000063]},"properties":{"OBJECTID":63,"ID":63,"X":596513.60419900005,"Y":3524718.7413209998,"Z":0,"地名":"团结河"}},{"type":"Feature","id":64,"geometry":{"type":"Point","coordinates":[120.89133273800007,31.744396169000026]},"properties":{"OBJECTID":64,"ID":64,"X":584394.24551499996,"Y":3513894.6108240001,"Z":0,"地名":"常通汽渡"}},{"type":"Feature","id":65,"geometry":{"type":"Point","coordinates":[120.84236318400008,31.753368369000043]},"properties":{"OBJECTID":65,"ID":65,"X":579746.23614099994,"Y":3514852.5879250001,"Z":0,"地名":"海洋泾"}},{"type":"Feature","id":66,"geometry":{"type":"Point","coordinates":[120.38696041000003,32.054488869000068]},"properties":{"OBJECTID":66,"ID":66,"X":536478.75274799997,"Y":3547999.1718290001,"Z":0,"地名":"夏仕港"}},{"type":"Feature","id":67,"geometry":{"type":"Point","coordinates":[120.78689118600005,31.836381622000033]},"properties":{"OBJECTID":67,"ID":67,"X":574423.70042000001,"Y":3524018.4307090002,"Z":0,"地名":"七干河"}},{"type":"Feature","id":68,"geometry":{"type":"Point","coordinates":[120.91077310200001,31.924673779000045]},"properties":{"OBJECTID":68,"ID":68,"X":586068.81718300004,"Y":3533900.855858,"Z":7,"地名":"营船港"}},{"type":"Feature","id":69,"geometry":{"type":"Point","coordinates":[120.92920264600002,31.889597784000046]},"properties":{"OBJECTID":69,"ID":69,"X":587845.13931400003,"Y":3530026.0195050002,"Z":0,"地名":"新开港"}},{"type":"Feature","id":70,"geometry":{"type":"Point","coordinates":[120.40027670500001,32.027632460000063]},"properties":{"OBJECTID":70,"ID":70,"X":537747.35062200006,"Y":3545025.6831419999,"Z":0,"地名":"福北水道"}},{"type":"Feature","id":71,"geometry":{"type":"Point","coordinates":[120.54595334700002,32.056355777000078]},"properties":{"OBJECTID":71,"ID":71,"X":551492.76977200003,"Y":3548271.0390189998,"Z":0,"地名":"如皋中汊"}},{"type":"Feature","id":72,"geometry":{"type":"Point","coordinates":[120.62309073300003,31.992614201000038]},"properties":{"OBJECTID":72,"ID":72,"X":558818.17315499997,"Y":3541242.1610579998,"Z":0,"地名":"浏海沙水道"}},{"type":"Feature","id":73,"geometry":{"type":"Point","coordinates":[120.88736338600006,31.860078906000069]},"properties":{"OBJECTID":73,"ID":73,"X":583913.43287799996,"Y":3526719.5115669998,"Z":0,"地名":"狼山沙东水道"}},{"type":"Feature","id":74,"geometry":{"type":"Point","coordinates":[120.85340370800009,31.821803045000024]},"properties":{"OBJECTID":74,"ID":74,"X":580732.79434499994,"Y":3522449.3552219998,"Z":0,"地名":"狼山沙西水道"}},{"type":"Feature","id":75,"geometry":{"type":"Point","coordinates":[120.7804680910001,31.949008400000025]},"properties":{"OBJECTID":75,"ID":75,"X":573725.80115900002,"Y":3536503.1663609999,"Z":0,"地名":"通州沙西水道"}},{"type":"Feature","id":76,"geometry":{"type":"Point","coordinates":[120.83056400200007,31.988813192000066]},"properties":{"OBJECTID":76,"ID":76,"X":578428.47330800002,"Y":3540952.4036409999,"Z":0,"地名":"通州沙东水道"}},{"type":"Feature","id":77,"geometry":{"type":"Point","coordinates":[120.88106683900003,31.82552792000007]},"properties":{"OBJECTID":77,"ID":77,"X":583348.59750799998,"Y":3522883.3042799998,"Z":0,"地名":"狼山沙"}},{"type":"Feature","id":78,"geometry":{"type":"Point","coordinates":[120.55263482200007,32.00736515400007]},"properties":{"OBJECTID":78,"ID":78,"X":552151.53034299996,"Y":3542841.6987490002,"Z":0,"地名":"浏海沙水道"}},{"type":"Feature","id":79,"geometry":{"type":"Point","coordinates":[120.66936339400002,32.047530884000025]},"properties":{"OBJECTID":79,"ID":79,"X":563153.38293600001,"Y":3547358.0188620002,"Z":0,"地名":"天生港水道"}},{"type":"Feature","id":80,"geometry":{"type":"Point","coordinates":[120.72218441900009,32.004803048000042]},"properties":{"OBJECTID":80,"ID":80,"X":568173.85282999999,"Y":3542652.019512,"Z":0,"地名":"南通水道"}},{"type":"Feature","id":81,"geometry":{"type":"Point","coordinates":[120.84724948900009,31.988019308000048]},"properties":{"OBJECTID":81,"ID":81,"X":580006.09219500003,"Y":3540876.5972569999,"Z":7,"地名":"姚港"}},{"type":"Feature","id":82,"geometry":{"type":"Point","coordinates":[120.88097532200004,31.771509482000056]},"properties":{"OBJECTID":82,"ID":82,"X":583388.45605599997,"Y":3516893.1780360001,"Z":0,"地名":"福山水道"}}]}